arranges/__init__.py
arranges/dict.py
arranges/ranges.py
arranges/segment.py
arranges/utils.py
arranges-0.2.3.dist-info/licenses/LICENSE.md
arranges-0.2.3.dist-info/WHEEL
arranges-0.2.3.dist-info/METADATA
arranges-0.2.3.dist-info/RECORD
