Metadata-Version: 2.4
Name: arranges
Version: 0.2.3
Summary: Mergeable range object for use in Pydantic classes
Author-email: Gareth Davidson <gaz@bitplane.net>
Requires-Python: >=3.11
Classifier: Programming Language :: Python :: 3
Classifier: License :: Public Domain
Classifier: Operating System :: OS Independent
Classifier: Topic :: Software Development :: Libraries :: Python Modules
License-File: LICENSE.md
Requires-Dist: pydantic ; extra == "dev"
Requires-Dist: flake8 ; extra == "dev"
Requires-Dist: pre-commit ; extra == "dev"
Requires-Dist: pytest ; extra == "dev"
Requires-Dist: pytest-cov ; extra == "dev"
Requires-Dist: coverage ; extra == "dev"
Requires-Dist: build ; extra == "dev"
Requires-Dist: twine ; extra == "dev"
Requires-Dist: pydoc-markdown ; extra == "dev"
Project-URL: Bug Tracker, https://github.com/bitplane/arranges/issues
Project-URL: Homepage, https://github.com/bitplane/arranges
Provides-Extra: dev
